ecs_tunnel/__init__.py
ecs_tunnel/_ecs_tunnel.py
ecs_tunnel/_version.py
ecs_tunnel/cli.py
ecs_tunnel-0.4.0.dist-info/LICENSE
ecs_tunnel-0.4.0.dist-info/METADATA
ecs_tunnel-0.4.0.dist-info/WHEEL
ecs_tunnel-0.4.0.dist-info/entry_points.txt
ecs_tunnel-0.4.0.dist-info/top_level.txt
ecs_tunnel-0.4.0.dist-info/RECORD
