Metadata-Version: 2.1
Name: ecs-tunnel
Version: 0.4.0
Summary: Tunnel ports via AWS ECS Tasks
Home-page: https://github.com/alastairmccormack/ecs-tunnel
Author: Alastair McCormack
Author-email: alastair@alumedia.co.uk
Project-URL: Bug Tracker, https://github.com/alastairmccormack/ecs-tunnel/issues
Classifier: Programming Language :: Python :: 3
Classifier: License :: OSI Approved :: MIT License
Classifier: Operating System :: OS Independent
Classifier: Topic :: Utilities
Classifier: Topic :: System :: Systems Administration
Classifier: Topic :: System :: Networking
Requires-Python: >=3.8
License-File: LICENSE
Requires-Dist: click
Requires-Dist: boto3
Requires-Dist: pexpect
Requires-Dist: jmespath
